CveXplore/.schema_version
CveXplore/LICENSE
CveXplore/VERSION
CveXplore/__init__.py
CveXplore/alembic.ini
CveXplore/cli.py
CveXplore/main.py
CveXplore/alembic/README
CveXplore/alembic/env.py
CveXplore/alembic/script.py.mako
CveXplore/alembic/versions/53df0e286532_first_2_models.py
CveXplore/alembic/versions/ecb1788b7e08_initial_full_model_setup.py
CveXplore/api/__init__.py
CveXplore/api/connection/__init__.py
CveXplore/api/connection/api_db.py
CveXplore/api/helpers/__init__.py
CveXplore/api/helpers/cve_search_api.py
CveXplore/cli_cmds/__init__.py
CveXplore/cli_cmds/capec_cmds/__init__.py
CveXplore/cli_cmds/capec_cmds/commands.py
CveXplore/cli_cmds/cli_utils/__init__.py
CveXplore/cli_cmds/cli_utils/utils.py
CveXplore/cli_cmds/cpe_cmds/__init__.py
CveXplore/cli_cmds/cpe_cmds/commands.py
CveXplore/cli_cmds/cve_cmds/__init__.py
CveXplore/cli_cmds/cve_cmds/commands.py
CveXplore/cli_cmds/cwe_cmds/__init__.py
CveXplore/cli_cmds/cwe_cmds/commands.py
CveXplore/cli_cmds/db_cmds/__init__.py
CveXplore/cli_cmds/db_cmds/commands.py
CveXplore/cli_cmds/find_cmds/__init__.py
CveXplore/cli_cmds/find_cmds/commands.py
CveXplore/cli_cmds/mutex_options/__init__.py
CveXplore/cli_cmds/mutex_options/mutex.py
CveXplore/cli_cmds/stats_cmds/__init__.py
CveXplore/cli_cmds/stats_cmds/commands.py
CveXplore/common/.env_example
CveXplore/common/.sources.ini
CveXplore/common/__init__.py
CveXplore/common/config.py
CveXplore/common/cpe_converters.py
CveXplore/common/data_source_connection.py
CveXplore/common/db_mapping.py
CveXplore/common/db_obj_mapping.py
CveXplore/core/__init__.py
CveXplore/core/api_base_class.py
CveXplore/core/database_actions/__init__.py
CveXplore/core/database_actions/db_action.py
CveXplore/core/database_indexer/__init__.py
CveXplore/core/database_indexer/db_indexer.py
CveXplore/core/database_maintenance/__init__.py
CveXplore/core/database_maintenance/api_handlers.py
CveXplore/core/database_maintenance/content_handlers.py
CveXplore/core/database_maintenance/download_handler.py
CveXplore-6561581.dist-info/LICENSE
CveXplore-6561581.dist-info/METADATA
CveXplore-6561581.dist-info/WHEEL
CveXplore-6561581.dist-info/entry_points.txt
CveXplore-6561581.dist-info/top_level.txt
CveXplore-6561581.dist-info/RECORD
