Metadata-Version: 2.1
Name: CveXplore
Version: 6561581
Summary: Package for interacting with cve-search
Home-page: https://github.com/cve-search/CveXplore
Author: Paul Tikken
Author-email: paul.tikken@gmail.com
License: GNU General Public License v3.0
Project-URL: Documentation, https://cve-search.github.io/CveXplore/
Project-URL: Issues, https://github.com/cve-search/CveXplore/issues
Classifier: License :: OSI Approved :: GNU General Public License v3 or later (GPLv3+)
Classifier: Programming Language :: Python :: 3
Classifier: Programming Language :: Python :: 3.10
Classifier: Programming Language :: Python :: 3.11
Classifier: Topic :: Software Development :: Libraries :: Python Modules
Classifier: Operating System :: OS Independent
Requires-Python: >=3.10
License-File: LICENSE
Requires-Dist: requests ==2.31.0
Requires-Dist: urllib3 >=2.0.6
Requires-Dist: tqdm ==4.66.1
Requires-Dist: python-dateutil ==2.8.2
Requires-Dist: click ==8.1.7
Requires-Dist: click-completion ==0.5.2
Requires-Dist: ijson >=3.2.3
Requires-Dist: ansicolors ==1.1.8
Requires-Dist: pygelf >=0.4.2
Requires-Dist: pandas >=2.1.2
Requires-Dist: dicttoxml ==1.7.16
Requires-Dist: python-dotenv ~=1.0.0
Requires-Dist: aiohttp >=3.8.6
Requires-Dist: aioretry >=5.0.2
Requires-Dist: pymongo >=4.5.0
Provides-Extra: all
Requires-Dist: pymongo >=4.5.0 ; extra == 'all'
Requires-Dist: alembic >=1.13.0 ; extra == 'all'
Requires-Dist: sqlalchemy >=2.0.23 ; extra == 'all'
Requires-Dist: sphinx ==7.2.6 ; extra == 'all'
Requires-Dist: sphinx-autodoc-typehints >=1.25.2 ; extra == 'all'
Requires-Dist: sphinx-rtd-theme ==1.3.0 ; extra == 'all'
Requires-Dist: PyMySQL >=1.1.0 ; extra == 'all'
Provides-Extra: docs
Requires-Dist: sphinx ==7.2.6 ; extra == 'docs'
Requires-Dist: sphinx-rtd-theme ==1.3.0 ; extra == 'docs'
Requires-Dist: sphinx-autodoc-typehints >=1.25.2 ; extra == 'docs'
Provides-Extra: kafka
Provides-Extra: mongodb
Requires-Dist: pymongo >=4.5.0 ; extra == 'mongodb'
Provides-Extra: mysql
Requires-Dist: sqlalchemy >=2.0.23 ; extra == 'mysql'
Requires-Dist: alembic >=1.13.0 ; extra == 'mysql'
Requires-Dist: PyMySQL >=1.1.0 ; extra == 'mysql'
Provides-Extra: postgres
Requires-Dist: sqlalchemy >=2.0.23 ; extra == 'postgres'
Requires-Dist: alembic >=1.13.0 ; extra == 'postgres'
Provides-Extra: redis
Provides-Extra: sqlalchemy
Requires-Dist: sqlalchemy >=2.0.23 ; extra == 'sqlalchemy'
Requires-Dist: alembic >=1.13.0 ; extra == 'sqlalchemy'
Provides-Extra: sqllite
Requires-Dist: sqlalchemy >=2.0.23 ; extra == 'sqllite'
Requires-Dist: alembic >=1.13.0 ; extra == 'sqllite'
